{
  "cards": [
    {"userId":"409042377","username":"Shadow_Bane97","cardId":80723580,"cardName":"Giant Trap Hole","rarity":"Rare","dateAdded":"2026-03-10"},
    {"userId":"409042377","username":"Shadow_Bane97","cardId":26561172,"cardName":"Myutant Mutant","rarity":"Common","dateAdded":"2026-03-10"},
    {"userId":"409042377","username":"Shadow_Bane97","cardId":34614289,"cardName":"U.A. Blockbacker","rarity":"Rare","dateAdded":"2026-03-10"},
    {"userId":"409042377","username":"Shadow_Bane97","cardId":101305027,"cardName":"Black Chaos the Dark Chaos Magician","rarity":"Common","dateAdded":"2026-03-10"},
    {"userId":"698909414","username":"popsongaming","cardId":45725480,"cardName":"Sacred Sword of Seven Stars","rarity":"Super","dateAdded":"2026-03-10"},
    {"userId":"698909414","username":"popsongaming","cardId":25034083,"cardName":"Decoyroid","rarity":"Common","dateAdded":"2026-03-10"},
    {"userId":"277880495","username":"GoEvan101New","cardId":97021916,"cardName":"Dark Resonator","rarity":"Rare","dateAdded":"2026-03-10"},
    {"userId":"277880495","username":"GoEvan101New","cardId":75499502,"cardName":"Master & Expert","rarity":"Common","dateAdded":"2026-03-10"},
    {"userId":"409042377","username":"Shadow_Bane97","cardId":12469386,"cardName":"Revival Rose","rarity":"Rare","dateAdded":"2026-03-10"},
    {"userId":"409042377","username":"Shadow_Bane97","cardId":59784896,"cardName":"Dark Zebra","rarity":"Common","dateAdded":"2026-03-10"},
    {"userId":"28587782","username":"iamfiref1y","cardId":60461077,"cardName":"Gouki Riscorpio","rarity":"Rare","dateAdded":"2026-03-10"},
    {"userId":"28587782","username":"iamfiref1y","cardId":85325774,"cardName":"Charge Into a Dark World","rarity":"Common","dateAdded":"2026-03-10"},
    {"userId":"409042377","username":"Shadow_Bane97","cardId":22959079,"cardName":"Dimensionhole","rarity":"Rare","dateAdded":"2026-03-10"},
    {"userId":"409042377","username":"Shadow_Bane97","cardId":66672569,"cardName":"Dragon Zombie","rarity":"Common","dateAdded":"2026-03-10"},
    {"userId":"810376108","username":"ImEighth","cardId":21516908,"cardName":"Hi-Speedroid Hagoita","rarity":"Rare","dateAdded":"2026-03-10"},
    {"userId":"810376108","username":"ImEighth","cardId":18585765,"cardName":"Voltester","rarity":"Common","dateAdded":"2026-03-10"},
    {"userId":"208179738","username":"E1337_13","cardId":19186123,"cardName":"Vision Release","rarity":"Ultra","dateAdded":"2026-03-10"},
    {"userId":"208179738","username":"E1337_13","cardId":25882881,"cardName":"Dokuroizo the Grim Reaper","rarity":"Common","dateAdded":"2026-03-10"},
    {"userId":"694889890","username":"MrBeanTheDino","cardId":22609617,"cardName":"Mataza the Zapper","rarity":"Rare","dateAdded":"2026-03-10"},
    {"userId":"694889890","username":"MrBeanTheDino","cardId":36042825,"cardName":"One-Shot Wand","rarity":"Rare","dateAdded":"2026-03-10"}
  ]
}
